Metadata-Version: 2.1
Name: ASI-distributions
Version: 0.1
Summary: Gaussian distributions
Home-page: UNKNOWN
Author: Andrew Ingalls
Author-email: ingallsandrew0@gmail.com
License: UNKNOWN
Platform: UNKNOWN
License-File: LICENSE
